nestpy/nestpy.cpython-310-darwin.so
nestpy_test2-1.5.18.dist-info/AUTHORS.md
nestpy_test2-1.5.18.dist-info/LICENSE
nestpy_test2-1.5.18.dist-info/METADATA
nestpy_test2-1.5.18.dist-info/WHEEL
nestpy_test2-1.5.18.dist-info/top_level.txt
nestpy_test2-1.5.18.dist-info/zip-safe
nestpy_test2-1.5.18.dist-info/RECORD
