Metadata-Version: 2.1
Name: nestpy-test2
Version: 1.5.18
Summary: Python bindings for the NEST noble element simulations
Home-page: UNKNOWN
Author: Sophia Farrell
Author-email: sja5@rice.edu
License: UNKNOWN
Project-URL: nestpy source, https://github.com/NESTCollaboration/nestpy
Project-URL: NEST library, https://github.com/NESTCollaboration/nest
Project-URL: NEST collaboration, http://nest.physics.ucdavis.edu/
Platform: UNKNOWN
Classifier: Development Status :: 5 - Production/Stable
Classifier: License :: OSI Approved :: GNU General Public License v3 (GPLv3)
Classifier: Natural Language :: English
Classifier: Programming Language :: Python :: 2.7
Classifier: Programming Language :: Python :: 3.4
Classifier: Programming Language :: Python :: 3.5
Classifier: Programming Language :: Python :: 3.6
Classifier: Programming Language :: Python :: 3.7
Classifier: Programming Language :: Python :: 3.8
Classifier: Programming Language :: Python :: 3.9
Classifier: Programming Language :: Python :: 3.10
Classifier: Programming Language :: C++
Classifier: Intended Audience :: Science/Research
Classifier: Programming Language :: Python :: Implementation :: CPython
Classifier: Topic :: Scientific/Engineering :: Physics
Classifier: Operating System :: MacOS :: MacOS X
Classifier: Operating System :: POSIX :: Linux
License-File: LICENSE
License-File: AUTHORS.md
Requires-Dist: numpy
